{
    "groups": {
        "agentcardproviders": {
            "plural": "agentcardproviders",
            "singular": "agentcardprovider",
            "modelversion": "1.0-rc1",
            "description": "Google A2A AgentCardProviders group",
            "resources": {
                "agentcards": {
                    "plural": "agentcards",
                    "singular": "agentcard",
                    "description": "Google A2A AgentCard resource",
                    "maxversions": 0,
                    "hasdocument": true,
                    "attributes": {
                        "specversion": {
                            "name": "specversion",
                            "type": "string",
                            "required": false,
                            "description": "Version of the A2A specification this agent card conforms to"
                        },
                        "*": {
                            "name": "*",
                            "type": "any",
                            "description": "Additional custom attributes allowed for agent card extensibility"
                        }
                    },
                    "metaattributes": {
                        "validation": {
                            "name": "validation",
                            "type": "boolean",
                            "required": true,
                            "default": false
                        }
                    }
                }
            }
        }
    }
} 