{
  "id": "ee33c4cb-5bdf-45c0-88a8-ba2d237189f9",
  "name": "io.github.neo4j-contrib/mcp-neo4j",
  "description": "Model Context Protocol with Neo4j",
  "repository": {
    "url": "https://github.com/neo4j-contrib/mcp-neo4j",
    "source": "github",
    "id": "897992568"
  },
  "version_detail": {
    "version": "0.0.1-seed",
    "release_date": "2025-05-16T19:00:42Z",
    "is_latest": true
  },
  "packages": [
    {
      "registry_name": "unknown",
      "name": "neo4j-contrib/mcp-neo4j",
      "version": ""
    }
  ],
  "tools": [],
  "resources": [],
  "prompts": []
}